chemex/__init__.py
chemex/__main__.py
chemex/chemex.py
chemex/cli.py
chemex/filterers.py
chemex/messages.py
chemex/toml.py
chemex/typing.py
chemex/uncertainty.py
chemex/configuration/__init__.py
chemex/configuration/base.py
chemex/configuration/conditions.py
chemex/configuration/data.py
chemex/configuration/experiment.py
chemex/configuration/methods.py
chemex/configuration/parameters.py
chemex/configuration/utils.py
chemex/containers/__init__.py
chemex/containers/data.py
chemex/containers/dataset.py
chemex/containers/experiment.py
chemex/containers/experiments.py
chemex/containers/profile.py
chemex/experiments/__init__.py
chemex/experiments/builder.py
chemex/experiments/factories.py
chemex/experiments/loader.py
chemex/experiments/catalog/__init__.py
chemex/experiments/catalog/cest_13c.py
chemex/experiments/catalog/cest_15n.py
chemex/experiments/catalog/cest_15n_cw.py
chemex/experiments/catalog/cest_15n_tr.py
chemex/experiments/catalog/cest_1hn_ap.py
chemex/experiments/catalog/cest_1hn_ip_ap.py
chemex/experiments/catalog/cest_ch3_1h_ip_ap.py
chemex/experiments/catalog/coscest_13c.py
chemex/experiments/catalog/coscest_1hn_ip_ap.py
chemex/experiments/catalog/cpmg_13c_ip.py
chemex/experiments/catalog/cpmg_13co_ap.py
chemex/experiments/catalog/cpmg_15n_ip.py
chemex/experiments/catalog/cpmg_15n_ip_0013.py
chemex/experiments/catalog/cpmg_15n_tr.py
chemex/experiments/catalog/cpmg_15n_tr_0013.py
chemex/experiments/catalog/cpmg_1hn_ap.py
chemex/experiments/catalog/cpmg_1hn_ap_0013.py
chemex/experiments/catalog/cpmg_ch3_13c_h2c.py
chemex/experiments/catalog/cpmg_ch3_1h_dq.py
chemex/experiments/catalog/cpmg_ch3_1h_sq.py
chemex/experiments/catalog/cpmg_ch3_1h_tq.py
chemex/experiments/catalog/cpmg_ch3_1h_tq_diff.py
chemex/experiments/catalog/cpmg_ch3_mq.py
chemex/experiments/catalog/cpmg_chd2_1h_ap.py
chemex/experiments/catalog/cpmg_hn_dq_zq.py
chemex/experiments/catalog/dcest_13c.py
chemex/experiments/catalog/dcest_15n.py
chemex/experiments/catalog/noesyfpgpph19.py
chemex-2025.4.0.dist-info/METADATA
chemex-2025.4.0.dist-info/WHEEL
chemex-2025.4.0.dist-info/entry_points.txt
chemex-2025.4.0.dist-info/licenses/LICENSE.md
chemex-2025.4.0.dist-info/RECORD
