Metadata-Version: 2.4
Name: chemex
Version: 2025.4.0
Summary: An analysis program for chemical exchange detected by NMR
Project-URL: Homepage, http://gbouvignies.github.io/ChemEx/
Project-URL: Documentation, http://gbouvignies.github.io/ChemEx/
Project-URL: Repository, https://github.com/gbouvignies/chemex
Project-URL: Changelog, https://github.com/gbouvignies/chemex/releases
Author-email: Guillaume Bouvignies <guillaume.bouvignies@ens.psl.eu>
License: ### GNU GENERAL PUBLIC LICENSE
License-File: LICENSE.md
Keywords: NMR,analysis,chemical exchange,spectroscopy
Classifier: Development Status :: 5 - Production/Stable
Classifier: Intended Audience :: Science/Research
Classifier: License :: OSI Approved :: GNU General Public License v3 or later (GPLv3+)
Classifier: Programming Language :: Python :: 3.12
Classifier: Programming Language :: Python :: 3.13
Classifier: Topic :: Scientific/Engineering :: Chemistry
Requires-Python: >=3.12
Requires-Dist: annotated-types>=0.7.0
Requires-Dist: cachetools>=5.5.1
Requires-Dist: emcee>=3.1.6
Requires-Dist: lmfit>=1.3.2
Requires-Dist: matplotlib>=3.10.0
Requires-Dist: numdifftools>=0.9.41
Requires-Dist: numpy>=2.2.3
Requires-Dist: pydantic>=2.10.6
Requires-Dist: rapidfuzz>=3.12.1
Requires-Dist: rich>=13.9.4
Requires-Dist: scipy>=1.15.2
